Workbook

Sheet Dashboard
B1: FINANCE / BUDGET TRACKER DASHBOARD
B2: ="Total Income"&CHAR(10)&TEXT(KPIs!B2,"$#,##0") -> Total Income $58,71,181 | F2: ="Total Expense"&CHAR(10)&TEXT(KPIs!B3,"$#,##0") -> Total Expense $50,12,022 | J2: ="Net Savings"&CHAR(10)&TEXT(KPIs!B4,"$#,##0") -> Net Savings $8,59,159 | N2: ="Savings Rate %"&CHAR(10)&TEXT(KPIs!B5,"0.0%") -> Savings Rate % 14.6% | R2: ="Over-Budget Txns"&CHAR(10)&TEXT(KPIs!B6,"0") -> Over-Budget Txns 491 | V2: ="Top Category"&CHAR(10)&KPIs!B7 -> Top Category Rent
W39: z

Sheet Transactions
A1: Transaction ID | B1: Date | C1: Month | D1: Type | E1: Category | F1: Sub-Category | G1: Description | H1: Payment Method | I1: Amount | J1: Budgeted Amount | K1: Account | L1: Recurring | M1: Budget Variance | N1: Signed Amount | O1: Over Budget Flag
A2: TXN-20988 | B2: 45293 | C2: Jan-2024 | D2: Expense | E2: Loan EMI | F2: Personal Loan EMI | G2: Personal Loan EMI payment | H2: Credit Card | I2: 14721.5 | J2: 12000 | K2: SBI Salary A/c | L2: Yes | M2: =IF(J2=0,"0",I2-J2) -> 2721.5 | N2: =IF(D2="Income",I2,-I2) -> -14721.5 | O2: =IF(M2>0,"Yes","No") -> Yes
A3: TXN-20310 | B3: 45294 | C3: Jan-2024 | D3: Expense | E3: Entertainment | F3: Movies | G3: Movies payment | H3: Net Banking | I3: 2992.04 | J3: 2500 | K3: Cash Wallet | L3: No | M3: =IF(J3=0,"0",I3-J3) -> 492.04 | N3: =IF(D3="Income",I3,-I3) -> -2992.04 | O3: =IF(M3>0,"Yes","No") -> Yes
A4: TXN-20978 | B4: 45294 | C4: Jan-2024 | D4: Expense | E4: Utilities | F4: Internet Bill | G4: Internet Bill payment | H4: Cash | I4: 1652.03 | J4: 3000 | K4: Cash Wallet | L4: Yes | M4: =IF(J4=0,"0",I4-J4) -> -1347.97 | N4: =IF(D4="Income",I4,-I4) -> -1652.03 | O4: =IF(M4>0,"Yes","No") -> No
A5: TXN-20461 | B5: 45294 | C5: Jan-2024 | D5: Expense | E5: Shopping | F5: Electronics | G5: Electronics payment | H5: UPI | I5: 3958.95 | J5: 4000 | K5: ICICI Credit Card | L5: No | M5: =IF(J5=0,"0",I5-J5) -> -41.05 | N5: =IF(D5="Income",I5,-I5) -> -3958.95 | O5: =IF(M5>0,"Yes","No") -> No
A6: TXN-20545 | B6: 45295 | C6: Jan-2024 | D6: Expense | E6: Groceries | F6: Supermarket | G6: Supermarket payment | H6: Credit Card | I6: 7132.33 | J6: 6000 | K6: ICICI Credit Card | L6: No | M6: =IF(J6=0,"0",I6-J6) -> 1132.33 | N6: =IF(D6="Income",I6,-I6) -> -7132.33 | O6: =IF(M6>0,"Yes","No") -> Yes
A7: TXN-20592 | B7: 45295 | C7: Jan-2024 | D7: Expense | E7: Rent | F7: House Rent | G7: House Rent payment | H7: Cash | I7: 13934.06 | J7: 15000 | K7: HDFC Savings | L7: Yes | M7: =IF(J7=0,"0",I7-J7) -> -1065.94 | N7: =IF(D7="Income",I7,-I7) -> -13934.06 | O7: =IF(M7>0,"Yes","No") -> No
A8: TXN-20744 | B8: 45295 | C8: Jan-2024 | D8: Expense | E8: Transport | F8: Cab/Taxi | G8: Cab/Taxi payment | H8: Debit Card | I8: 4262.73 | J8: 3500 | K8: SBI Salary A/c | L8: No | M8: =IF(J8=0,"0",I8-J8) -> 762.73 | N8: =IF(D8="Income",I8,-I8) -> -4262.73 | O8: =IF(M8>0,"Yes","No") -> Yes
A9: TXN-20184 | B9: 45296 | C9: Jan-2024 | D9: Income | E9: Salary | F9: Monthly Salary | G9: Monthly Salary received | H9: UPI | I9: 51320.36 | J9: 0 | K9: ICICI Credit Card | L9: Yes | M9: =IF(J9=0,"0",I9-J9) -> 0 | N9: =IF(D9="Income",I9,-I9) -> 51320.36 | O9: =IF(M9>0,"Yes","No") -> Yes
A10: TXN-20096 | B10: 45298 | C10: Jan-2024 | D10: Expense | E10: Shopping | F10: Electronics | G10: Electronics payment | H10: Debit Card | I10: 2155.51 | J10: 4000 | K10: SBI Salary A/c | L10: Yes | M10: =IF(J10=0,"0",I10-J10) -> -1844.49 | N10: =IF(D10="Income",I10,-I10) -> -2155.51 | O10: =IF(M10>0,"Yes","No") -> No
A11: TXN-20878 | B11: 45299 | C11: Jan-2024 | D11: Expense | E11: Loan EMI | F11: Home Loan EMI | G11: Home Loan EMI payment | H11: UPI | I11: 12191.71 | J11: 12000 | K11: HDFC Savings | L11: Yes | M11: =IF(J11=0,"0",I11-J11) -> 191.71 | N11: =IF(D11="Income",I11,-I11) -> -12191.71 | O11: =IF(M11>0,"Yes","No") -> Yes
A12: TXN-20755 | B12: 45300 | C12: Jan-2024 | D12: Income | E12: Salary | F12: Monthly Salary | G12: Monthly Salary received | H12: UPI | I12: 51405.21 | J12: 0 | K12: ICICI Credit Card | L12: Yes | M12: =IF(J12=0,"0",I12-J12) -> 0 | N12: =IF(D12="Income",I12,-I12) -> 51405.21 | O12: =IF(M12>0,"Yes","No") -> Yes
A13: TXN-20315 | B13: 45300 | C13: Jan-2024 | D13: Income | E13: Salary | F13: Monthly Salary | G13: Monthly Salary received | H13: Net Banking | I13: 43740.05 | J13: 0 | K13: Cash Wallet | L13: Yes | M13: =IF(J13=0,"0",I13-J13) -> 0 | N13: =IF(D13="Income",I13,-I13) -> 43740.05 | O13: =IF(M13>0,"Yes","No") -> Yes
... A1001: TXN-20837 | B1001: 45835 | C1001: Jun-2025 | D1001: Expense | E1001: Rent | F1001: House Rent | G1001: House Rent payment | H1001: UPI | I1001: 15077.13 | J1001: 15000 | K1001: HDFC Savings | L1001: Yes | M1001: =IF(J1001=0,"0",I1001-J1001) -> 77.13 | N1001: =IF(D1001="Income",I1001,-I1001) -> -15077.13 | O1001: =IF(M1001>0,"Yes","No") -> Yes

Sheet KPIs
A1: KPIs | B1: Values
A2: Total Income | B2: =SUMIF(Transactions!D2:D1001,"Income",Transactions!I2:I1001) -> 5871180.5
A3: Total Expense | B3: =SUMIF(Transactions!D2:D1001,"Expense",Transactions!I2:I1001) -> 5012021.7
A4: Net Savings | B4: =B2-B3 -> 859158.82
A5: Savings Rate % | B5: =B4/B2 -> 0.14633494
A6: Over-Budget Transactions | B6: =COUNTIF(Transactions!O2:O1001,"Yes") -> 491
A7: Top Spending Category | B7: =INDEX(A11:A20,MATCH(MAX(B11:B20),B11:B20,0)) -> Rent
A9: Category Totals (helper)
A10: Category | B10: Total Spend
A11: Rent | B11: =SUMIF(Transactions!$E$2:$E$1001,A11,Transactions!$I$2:$I$1001) -> 1341567.9
A12: Groceries | B12: =SUMIF(Transactions!$E$2:$E$1001,A12,Transactions!$I$2:$I$1001) -> 646572.01
A13: Utilities | B13: =SUMIF(Transactions!$E$2:$E$1001,A13,Transactions!$I$2:$I$1001) -> 223500.02
A14: Transport | B14: =SUMIF(Transactions!$E$2:$E$1001,A14,Transactions!$I$2:$I$1001) -> 249290.25
A15: Entertainment | B15: =SUMIF(Transactions!$E$2:$E$1001,A15,Transactions!$I$2:$I$1001) -> 177742.46
A16: Healthcare | B16: =SUMIF(Transactions!$E$2:$E$1001,A16,Transactions!$I$2:$I$1001) -> 124251.52
A17: Shopping | B17: =SUMIF(Transactions!$E$2:$E$1001,A17,Transactions!$I$2:$I$1001) -> 273040.46
A18: Savings/Investment | B18: =SUMIF(Transactions!$E$2:$E$1001,A18,Transactions!$I$2:$I$1001) -> 672058.86
A19: Loan EMI | B19: =SUMIF(Transactions!$E$2:$E$1001,A19,Transactions!$I$2:$I$1001) -> 1242239.1
A20: Education | B20: =SUMIF(Transactions!$E$2:$E$1001,A20,Transactions!$I$2:$I$1001) -> 61759.1

Sheet PT_BudgetVsActual
A3: Row Labels | B3: Actual Spend | C3: Sum of Budgeted Amount
A4: Education | B4: 61759.1 | C4: 68000
A5: Entertainment | B5: 177742.46 | C5: 200000
A6: Groceries | B6: 646572.01 | C6: 720000
A7: Healthcare | B7: 124251.52 | C7: 136000
A8: Loan EMI | B8: 1242239.1 | C8: 1344000
A9: Rent | B9: 1341567.9 | C9: 1485000
A10: Savings/Investment | B10: 672058.86 | C10: 720000
A11: Shopping | B11: 273040.46 | C11: 292000
A12: Transport | B12: 249290.25 | C12: 280000
A13: Utilities | B13: 223500.02 | C13: 249000
A14: Grand Total | B14: 5012021.7 | C14: 5494000

Sheet PT_Recurring
A3: Row Labels | B3: Sum of Amount
A4: Yes | B4: 3747263
A5: Education | B5: 3650.91
A6: Entertainment | B6: 35450.63
A7: Groceries | B7: 117380.14
A8: Healthcare | B8: 25201.4
A9: Loan EMI | B9: 1242239.1
A10: Rent | B10: 1341567.9
A11: Savings/Investment | B11: 672058.86
A12: Shopping | B12: 66457.85
A13: Transport | B13: 19756.18
A14: Utilities | B14: 223500.02
A15: No | B15: 1264758.7
... A22: Grand Total | B22: 5012021.7

Sheet PT_Trend
A3: Sum of Amount | B3: Column Labels
A4: Row Labels | B4: Expense | C4: Income | D4: Grand Total
A5: 2024 | B5: 3420132.3 | C5: 4052766.4 | D5: 7472898.7
A6: Jan | B6: 257734.59 | C6: 453311.73 | D6: 711046.32
A7: Feb | B7: 318652.68 | C7: 379354.46 | D7: 698007.14
A8: Mar | B8: 313100.68 | C8: 278131.33 | D8: 591232.01
A9: Apr | B9: 307327.2 | C9: 388203.17 | D9: 695530.37
A10: May | B10: 181933.57 | C10: 262754.41 | D10: 444687.98
A11: Jun | B11: 261055.28 | C11: 372829.78 | D11: 633885.06
A12: Jul | B12: 263095.67 | C12: 365604.99 | D12: 628700.66
A13: Aug | B13: 252601.86 | C13: 322980.42 | D13: 575582.28
A14: Sep | B14: 254904.44 | C14: 255004.33 | D14: 509908.77
A15: Oct | B15: 383381.88 | C15: 305399.59 | D15: 688781.47
A16: Nov | B16: 248573.13 | C16: 314855.79 | D16: 563428.92
... A25: Grand Total | B25: 5012021.7 | C25: 5871180.5 | D25: 10883202

Sheet PT_Category
A3: Row Labels | B3: Sum of Amount
A4: Education | B4: 61759.1
A5: Entertainment | B5: 177742.46
A6: Groceries | B6: 646572.01
A7: Healthcare | B7: 124251.52
A8: Loan EMI | B8: 1242239.1
A9: Rent | B9: 1341567.9
A10: Savings/Investment | B10: 672058.86
A11: Shopping | B11: 273040.46
A12: Transport | B12: 249290.25
A13: Utilities | B13: 223500.02
A14: Grand Total | B14: 5012021.7
